camsaxs/__init__.py
camsaxs/config.yml
camsaxs/cwt.py
camsaxs/factory.py
camsaxs/fit_sasmodel.py
camsaxs/loader.py
camsaxs/remesh.py
camsaxs/remesh_bbox.py
camsaxs/warp_image.py
camsaxs-1.0.3.dist-info/METADATA
camsaxs-1.0.3.dist-info/WHEEL
camsaxs-1.0.3.dist-info/top_level.txt
camsaxs-1.0.3.dist-info/RECORD
