Metadata-Version: 2.1
Name: camsaxs
Version: 1.0.3
Summary: Xi-cam.SAXS companion functions
Home-page: http://github.com/lbl-camera/CamSAXS
Author: Dinesh Kumar
Author-email: dkumar@lbl.gov
License: UNKNOWN
Platform: UNKNOWN
Requires-Dist: numpy
Requires-Dist: scipy
Requires-Dist: astropy
Requires-Dist: pyFAI
Requires-Dist: sasmodels
Requires-Dist: pyyaml
